osqua/__init__.py
osqua/x.py
osqua-0.0.1.dist-info/LICENSE
osqua-0.0.1.dist-info/METADATA
osqua-0.0.1.dist-info/WHEEL
osqua-0.0.1.dist-info/top_level.txt
osqua-0.0.1.dist-info/RECORD
