Metadata-Version: 2.1
Name: osqua
Version: 0.0.1
Summary: Osqua package for simulating quantum computing based on oscillatory quota
Home-page: https://github.com/lapyl/osqua
Author: Lalit Patel
Author-email: llsr@att.net
Classifier: Programming Language :: Python :: 3
Classifier: License :: OSI Approved :: MIT License
Classifier: Operating System :: OS Independent
Requires-Python: >=3.6
License-File: LICENSE
Requires-Dist: networkx
Requires-Dist: matplotlib
